aidevkit/__init__.py
aidevkit/aos.py
aidevkit/component.py
aidevkit/ga.py
aidevkit-0.3.3.dist-info/LICENSE
aidevkit-0.3.3.dist-info/METADATA
aidevkit-0.3.3.dist-info/WHEEL
aidevkit-0.3.3.dist-info/top_level.txt
aidevkit-0.3.3.dist-info/RECORD
