Metadata-Version: 2.1
Name: aidevkit
Version: 0.3.3
Summary: 一些ai开发过程中使用到的工具模块
Home-page: https://github.com/cpcgskill/aidevkit
Author: cpcgskill
Author-email: cpcgskill@outlook.com
License: Apache Software License (Apache 2.0)
Project-URL: Bug Tracker, https://github.com/cpcgskill/aidevkit/issues
Classifier: License :: OSI Approved :: Apache Software License
Classifier: Programming Language :: Python
Classifier: Programming Language :: Python :: 2
Classifier: Programming Language :: Python :: 2.7
Classifier: Programming Language :: Python :: 3
Classifier: Programming Language :: Python :: 3.6
Classifier: Programming Language :: Python :: 3.7
Classifier: Programming Language :: Python :: 3.8
Classifier: Programming Language :: Python :: 3.9
Classifier: Programming Language :: Python :: 3.10
Classifier: Programming Language :: Python :: Implementation :: CPython
Requires-Python: >=2.7, !=3.0.*, !=3.1.*, !=3.2.*, !=3.3.*, !=3.4.*, !=3.5.*
License-File: LICENSE
Requires-Dist: torch
Requires-Dist: setuptools
Requires-Dist: transformers
Requires-Dist: datasets
Requires-Dist: tokenizers
Requires-Dist: accelerate
Requires-Dist: sentencepiece
Requires-Dist: apache-beam
Requires-Dist: mwparserfromhell
Requires-Dist: hnswlib
Requires-Dist: cos-python-sdk-v5
